{
    "cardId": 30111,
    "cardName": "[智]东海",
    "cardSkill": {
        "SkillList": 0,
        "skillNum": 0
    },
    "cardType": 4,
    "cardValue": [
        {
            "filled": false
        },
        {
            "filled": false
        },
        {
            "filled": false
        },
        {
            "filled": false
        },
        {
            "bonus": [
                1.0,
                0.0,
                0.0,
                0.0,
                2.0,
                0.0
            ],
            "deYiLv": 35.0,
            "failRateDrop": 0.0,
            "filled": true,
            "ganJing": 0.0,
            "hintBonus": [
                0,
                0,
                0,
                0,
                0,
                20
            ],
            "hintProbIncrease": 40.0,
            "initialBonus": [
                0,
                0,
                0,
                0,
                0,
                0
            ],
            "initialJiBan": 20,
            "saiHou": 5.0,
            "vitalCostDrop": 0.0,
            "wizVitalBonus": 5,
            "xunLian": 20.0,
            "youQing": 30.0
        }
    ]
}